aims_io/__init__.py
aims_io/aims_io.py
aims_io-0.3.1.dist-info/METADATA
aims_io-0.3.1.dist-info/WHEEL
aims_io-0.3.1.dist-info/RECORD
